[
  {
    "category": "top",
    "title": "Crop Top",
    "price": 153.7
  },
  {
    "category": "top",
    "title": "Button-Down Oxford",
    "price": 135.95
  },
  {
    "category": "top",
    "title": "Off-Shoulder Blouse",
    "price": 161.1
  },
  {
    "category": "top",
    "title": "Casual Henley",
    "price": 99.24
  },
  {
    "category": "top",
    "title": "Patterned Blouse",
    "price": 44.52
  },
  {
    "category": "top",
    "title": "Tank Top",
    "price": 57.86
  },
  {
    "category": "top",
    "title": "Flannel Shirt",
    "price": 26.5
  },
  {
    "category": "top",
    "title": "Denim Jacket",
    "price": 61.52
  },
  {
    "category": "top",
    "title": "Silk Camisole",
    "price": 34.16
  },
  {
    "category": "top",
    "title": "Patterned Blouse",
    "price": 24.45
  },
  {
    "category": "top",
    "title": "Button-Down Oxford",
    "price": 196.32
  },
  {
    "category": "top",
    "title": "Denim Jacket",
    "price": 109.01
  },
  {
    "category": "top",
    "title": "Graphic Tee",
    "price": 48.5
  },
  {
    "category": "top",
    "title": "Casual Henley",
    "price": 94.24
  },
  {
    "category": "top",
    "title": "Turtleneck",
    "price": 147.37
  },
  {
    "category": "top",
    "title": "Silk Camisole",
    "price": 27.16
  },
  {
    "category": "top",
    "title": "Hoodie",
    "price": 155.9
  },
  {
    "category": "top",
    "title": "Crewneck Sweatshirt",
    "price": 101.94
  },
  {
    "category": "top",
    "title": "Flannel Shirt",
    "price": 151.28
  },
  {
    "category": "top",
    "title": "Patterned Blouse",
    "price": 171.67
  },
  {
    "category": "top",
    "title": "Denim Jacket",
    "price": 56.14
  },
  {
    "category": "top",
    "title": "Patterned Blouse",
    "price": 48.86
  },
  {
    "category": "top",
    "title": "Classic Cotton T-Shirt",
    "price": 176.28
  },
  {
    "category": "top",
    "title": "V-Neck Sweater",
    "price": 61.74
  },
  {
    "category": "top",
    "title": "Crop Top",
    "price": 63.06
  },
  {
    "category": "top",
    "title": "Patterned Blouse",
    "price": 183.22
  },
  {
    "category": "top",
    "title": "Tank Top",
    "price": 130.41
  },
  {
    "category": "top",
    "title": "Long Sleeve Thermal",
    "price": 97.05
  },
  {
    "category": "top",
    "title": "Patterned Blouse",
    "price": 27.49
  },
  {
    "category": "top",
    "title": "Casual Henley",
    "price": 41.71
  },
  {
    "category": "top",
    "title": "Flannel Shirt",
    "price": 190.74
  },
  {
    "category": "top",
    "title": "Button-Down Oxford",
    "price": 188.37
  },
  {
    "category": "top",
    "title": "Button-Down Oxford",
    "price": 59.42
  },
  {
    "category": "top",
    "title": "Crewneck Sweatshirt",
    "price": 74.35
  },
  {
    "category": "top",
    "title": "Denim Jacket",
    "price": 106.66
  },
  {
    "category": "top",
    "title": "Graphic Tee",
    "price": 14.5
  },
  {
    "category": "top",
    "title": "Cardigan",
    "price": 158.18
  },
  {
    "category": "top",
    "title": "Crop Top",
    "price": 22.49
  },
  {
    "category": "top",
    "title": "Button-Down Oxford",
    "price": 54.31
  },
  {
    "category": "top",
    "title": "Classic Cotton T-Shirt",
    "price": 148.17
  },
  {
    "category": "top",
    "title": "Button-Down Oxford",
    "price": 124.82
  },
  {
    "category": "top",
    "title": "Hoodie",
    "price": 131.38
  },
  {
    "category": "top",
    "title": "Casual Henley",
    "price": 168.11
  },
  {
    "category": "top",
    "title": "Off-Shoulder Blouse",
    "price": 14.89
  },
  {
    "category": "top",
    "title": "Hoodie",
    "price": 102.38
  },
  {
    "category": "top",
    "title": "Hoodie",
    "price": 122.7
  },
  {
    "category": "top",
    "title": "Long Sleeve Thermal",
    "price": 82.03
  },
  {
    "category": "top",
    "title": "Silk Camisole",
    "price": 184.96
  },
  {
    "category": "top",
    "title": "Classic Cotton T-Shirt",
    "price": 39.58
  },
  {
    "category": "top",
    "title": "Flannel Shirt",
    "price": 84.16
  },
  {
    "category": "top",
    "title": "Crop Top",
    "price": 149.78
  },
  {
    "category": "top",
    "title": "Casual Henley",
    "price": 24.03
  },
  {
    "category": "top",
    "title": "Off-Shoulder Blouse",
    "price": 125.01
  },
  {
    "category": "top",
    "title": "Cardigan",
    "price": 134.62
  },
  {
    "category": "top",
    "title": "V-Neck Sweater",
    "price": 113.6
  },
  {
    "category": "top",
    "title": "Off-Shoulder Blouse",
    "price": 99.31
  },
  {
    "category": "top",
    "title": "Tank Top",
    "price": 99.71
  },
  {
    "category": "top",
    "title": "Flannel Shirt",
    "price": 119.59
  },
  {
    "category": "top",
    "title": "Graphic Tee",
    "price": 185.95
  },
  {
    "category": "top",
    "title": "Hoodie",
    "price": 18.3
  },
  {
    "category": "top",
    "title": "Hoodie",
    "price": 158.76
  },
  {
    "category": "top",
    "title": "Linen Shirt",
    "price": 156.11
  },
  {
    "category": "top",
    "title": "Button-Down Oxford",
    "price": 109.35
  },
  {
    "category": "top",
    "title": "Patterned Blouse",
    "price": 37.99
  },
  {
    "category": "top",
    "title": "Cardigan",
    "price": 95.14
  },
  {
    "category": "top",
    "title": "Denim Jacket",
    "price": 183.4
  },
  {
    "category": "top",
    "title": "Hoodie",
    "price": 28.17
  },
  {
    "category": "top",
    "title": "Silk Camisole",
    "price": 48.81
  },
  {
    "category": "top",
    "title": "Crop Top",
    "price": 125.44
  },
  {
    "category": "top",
    "title": "Crop Top",
    "price": 196.84
  },
  {
    "category": "top",
    "title": "Casual Henley",
    "price": 144.71
  },
  {
    "category": "top",
    "title": "Crewneck Sweatshirt",
    "price": 107.5
  },
  {
    "category": "top",
    "title": "Tank Top",
    "price": 112.98
  },
  {
    "category": "top",
    "title": "Turtleneck",
    "price": 24.26
  },
  {
    "category": "top",
    "title": "Crop Top",
    "price": 46.72
  },
  {
    "category": "top",
    "title": "Button-Down Oxford",
    "price": 58.15
  },
  {
    "category": "top",
    "title": "Long Sleeve Thermal",
    "price": 182.64
  },
  {
    "category": "top",
    "title": "Button-Down Oxford",
    "price": 95.15
  },
  {
    "category": "top",
    "title": "Cardigan",
    "price": 114.21
  },
  {
    "category": "top",
    "title": "Tank Top",
    "price": 162.71
  },
  {
    "category": "top",
    "title": "V-Neck Sweater",
    "price": 114.27
  },
  {
    "category": "top",
    "title": "Tank Top",
    "price": 33.84
  },
  {
    "category": "top",
    "title": "Off-Shoulder Blouse",
    "price": 10.32
  },
  {
    "category": "top",
    "title": "Off-Shoulder Blouse",
    "price": 197.75
  },
  {
    "category": "top",
    "title": "Tank Top",
    "price": 178.56
  },
  {
    "category": "top",
    "title": "Silk Camisole",
    "price": 162.75
  },
  {
    "category": "top",
    "title": "Patterned Blouse",
    "price": 118.7
  },
  {
    "category": "top",
    "title": "Graphic Tee",
    "price": 140.09
  },
  {
    "category": "top",
    "title": "Graphic Tee",
    "price": 196.74
  },
  {
    "category": "top",
    "title": "Hoodie",
    "price": 96.03
  },
  {
    "category": "top",
    "title": "Linen Shirt",
    "price": 41.63
  },
  {
    "category": "top",
    "title": "Flannel Shirt",
    "price": 16.88
  },
  {
    "category": "top",
    "title": "Tank Top",
    "price": 29.74
  },
  {
    "category": "top",
    "title": "Silk Camisole",
    "price": 75.84
  },
  {
    "category": "top",
    "title": "Turtleneck",
    "price": 29.75
  },
  {
    "category": "top",
    "title": "Tank Top",
    "price": 144.62
  },
  {
    "category": "top",
    "title": "Casual Henley",
    "price": 152.0
  },
  {
    "category": "top",
    "title": "Tank Top",
    "price": 182.71
  },
  {
    "category": "top",
    "title": "Long Sleeve Thermal",
    "price": 146.78
  },
  {
    "category": "top",
    "title": "Classic Cotton T-Shirt",
    "price": 138.69
  },
  {
    "category": "bottom",
    "title": "Chino Pants",
    "price": 170.26
  },
  {
    "category": "bottom",
    "title": "Chino Pants",
    "price": 188.24
  },
  {
    "category": "bottom",
    "title": "Bermuda Shorts",
    "price": 109.26
  },
  {
    "category": "bottom",
    "title": "Dress Pants",
    "price": 61.18
  },
  {
    "category": "bottom",
    "title": "Track Pants",
    "price": 175.32
  },
  {
    "category": "bottom",
    "title": "Pleated Skirt",
    "price": 68.81
  },
  {
    "category": "bottom",
    "title": "High-Waisted Jeans",
    "price": 67.75
  },
  {
    "category": "bottom",
    "title": "Denim Shorts",
    "price": 14.03
  },
  {
    "category": "bottom",
    "title": "Maxi Skirt",
    "price": 10.37
  },
  {
    "category": "bottom",
    "title": "Pleated Skirt",
    "price": 109.95
  },
  {
    "category": "bottom",
    "title": "Athletic Joggers",
    "price": 180.08
  },
  {
    "category": "bottom",
    "title": "Chino Pants",
    "price": 55.52
  },
  {
    "category": "bottom",
    "title": "Denim Shorts",
    "price": 157.49
  },
  {
    "category": "bottom",
    "title": "Pencil Skirt",
    "price": 164.75
  },
  {
    "category": "bottom",
    "title": "Distressed Jeans",
    "price": 89.54
  },
  {
    "category": "bottom",
    "title": "A-Line Skirt",
    "price": 30.23
  },
  {
    "category": "bottom",
    "title": "Athletic Joggers",
    "price": 190.38
  },
  {
    "category": "bottom",
    "title": "Pleated Skirt",
    "price": 91.02
  },
  {
    "category": "bottom",
    "title": "Pencil Skirt",
    "price": 25.27
  },
  {
    "category": "bottom",
    "title": "Pencil Skirt",
    "price": 39.23
  },
  {
    "category": "bottom",
    "title": "Leather Leggings",
    "price": 130.96
  },
  {
    "category": "bottom",
    "title": "Athletic Joggers",
    "price": 57.71
  },
  {
    "category": "bottom",
    "title": "Chino Pants",
    "price": 195.45
  },
  {
    "category": "bottom",
    "title": "Corduroy Pants",
    "price": 148.1
  },
  {
    "category": "bottom",
    "title": "Palazzo Pants",
    "price": 188.71
  },
  {
    "category": "bottom",
    "title": "Maxi Skirt",
    "price": 177.12
  },
  {
    "category": "bottom",
    "title": "Linen Trousers",
    "price": 167.92
  },
  {
    "category": "bottom",
    "title": "Dress Pants",
    "price": 107.88
  },
  {
    "category": "bottom",
    "title": "Palazzo Pants",
    "price": 164.84
  },
  {
    "category": "bottom",
    "title": "Dress Pants",
    "price": 42.39
  },
  {
    "category": "bottom",
    "title": "High-Waisted Jeans",
    "price": 146.62
  },
  {
    "category": "bottom",
    "title": "Corduroy Pants",
    "price": 126.92
  },
  {
    "category": "bottom",
    "title": "Distressed Jeans",
    "price": 132.33
  },
  {
    "category": "bottom",
    "title": "A-Line Skirt",
    "price": 176.83
  },
  {
    "category": "bottom",
    "title": "Pencil Skirt",
    "price": 13.94
  },
  {
    "category": "bottom",
    "title": "Khaki Pants",
    "price": 114.38
  },
  {
    "category": "bottom",
    "title": "Athletic Joggers",
    "price": 21.27
  },
  {
    "category": "bottom",
    "title": "Maxi Skirt",
    "price": 124.92
  },
  {
    "category": "bottom",
    "title": "Khaki Pants",
    "price": 156.53
  },
  {
    "category": "bottom",
    "title": "Culottes",
    "price": 173.02
  },
  {
    "category": "bottom",
    "title": "Corduroy Pants",
    "price": 69.0
  },
  {
    "category": "bottom",
    "title": "Leather Leggings",
    "price": 80.94
  },
  {
    "category": "bottom",
    "title": "Pencil Skirt",
    "price": 101.58
  },
  {
    "category": "bottom",
    "title": "Khaki Pants",
    "price": 74.13
  },
  {
    "category": "bottom",
    "title": "Bermuda Shorts",
    "price": 65.99
  },
  {
    "category": "bottom",
    "title": "Denim Shorts",
    "price": 57.27
  },
  {
    "category": "bottom",
    "title": "High-Waisted Jeans",
    "price": 173.73
  },
  {
    "category": "bottom",
    "title": "Linen Trousers",
    "price": 74.99
  },
  {
    "category": "bottom",
    "title": "Palazzo Pants",
    "price": 115.89
  },
  {
    "category": "bottom",
    "title": "Dress Pants",
    "price": 135.69
  },
  {
    "category": "bottom",
    "title": "Athletic Joggers",
    "price": 59.92
  },
  {
    "category": "bottom",
    "title": "Corduroy Pants",
    "price": 87.98
  },
  {
    "category": "bottom",
    "title": "Linen Trousers",
    "price": 190.65
  },
  {
    "category": "bottom",
    "title": "Cargo Shorts",
    "price": 161.69
  },
  {
    "category": "bottom",
    "title": "Slim Fit Jeans",
    "price": 107.6
  },
  {
    "category": "bottom",
    "title": "Denim Shorts",
    "price": 173.48
  },
  {
    "category": "bottom",
    "title": "Denim Shorts",
    "price": 17.14
  },
  {
    "category": "bottom",
    "title": "Distressed Jeans",
    "price": 37.84
  },
  {
    "category": "bottom",
    "title": "High-Waisted Jeans",
    "price": 163.32
  },
  {
    "category": "bottom",
    "title": "Linen Trousers",
    "price": 48.27
  },
  {
    "category": "bottom",
    "title": "High-Waisted Jeans",
    "price": 165.61
  },
  {
    "category": "bottom",
    "title": "Distressed Jeans",
    "price": 93.37
  },
  {
    "category": "bottom",
    "title": "Denim Shorts",
    "price": 22.42
  },
  {
    "category": "bottom",
    "title": "Chino Pants",
    "price": 42.89
  },
  {
    "category": "bottom",
    "title": "Linen Trousers",
    "price": 26.16
  },
  {
    "category": "bottom",
    "title": "Maxi Skirt",
    "price": 63.75
  },
  {
    "category": "bottom",
    "title": "Bermuda Shorts",
    "price": 136.03
  },
  {
    "category": "bottom",
    "title": "A-Line Skirt",
    "price": 44.12
  },
  {
    "category": "bottom",
    "title": "Denim Shorts",
    "price": 13.74
  },
  {
    "category": "bottom",
    "title": "Culottes",
    "price": 121.61
  },
  {
    "category": "bottom",
    "title": "Track Pants",
    "price": 190.1
  },
  {
    "category": "bottom",
    "title": "Pencil Skirt",
    "price": 189.56
  },
  {
    "category": "bottom",
    "title": "Track Pants",
    "price": 131.07
  },
  {
    "category": "bottom",
    "title": "Distressed Jeans",
    "price": 33.03
  },
  {
    "category": "bottom",
    "title": "Dress Pants",
    "price": 159.3
  },
  {
    "category": "bottom",
    "title": "Leather Leggings",
    "price": 156.82
  },
  {
    "category": "bottom",
    "title": "Corduroy Pants",
    "price": 183.0
  },
  {
    "category": "bottom",
    "title": "Culottes",
    "price": 31.1
  },
  {
    "category": "bottom",
    "title": "Athletic Joggers",
    "price": 162.22
  },
  {
    "category": "bottom",
    "title": "Leather Leggings",
    "price": 58.0
  },
  {
    "category": "bottom",
    "title": "Linen Trousers",
    "price": 99.82
  },
  {
    "category": "bottom",
    "title": "Chino Pants",
    "price": 34.14
  },
  {
    "category": "bottom",
    "title": "Slim Fit Jeans",
    "price": 137.73
  },
  {
    "category": "bottom",
    "title": "Corduroy Pants",
    "price": 134.55
  },
  {
    "category": "bottom",
    "title": "High-Waisted Jeans",
    "price": 72.79
  },
  {
    "category": "bottom",
    "title": "Distressed Jeans",
    "price": 29.74
  },
  {
    "category": "bottom",
    "title": "Leather Leggings",
    "price": 174.95
  },
  {
    "category": "bottom",
    "title": "Dress Pants",
    "price": 30.65
  },
  {
    "category": "bottom",
    "title": "Athletic Joggers",
    "price": 133.53
  },
  {
    "category": "bottom",
    "title": "Khaki Pants",
    "price": 68.79
  },
  {
    "category": "bottom",
    "title": "Denim Shorts",
    "price": 33.52
  },
  {
    "category": "bottom",
    "title": "High-Waisted Jeans",
    "price": 83.96
  },
  {
    "category": "bottom",
    "title": "Bermuda Shorts",
    "price": 39.84
  },
  {
    "category": "bottom",
    "title": "Track Pants",
    "price": 114.22
  },
  {
    "category": "bottom",
    "title": "Athletic Joggers",
    "price": 117.58
  },
  {
    "category": "bottom",
    "title": "Chino Pants",
    "price": 125.25
  },
  {
    "category": "bottom",
    "title": "Slim Fit Jeans",
    "price": 19.86
  },
  {
    "category": "bottom",
    "title": "Corduroy Pants",
    "price": 20.12
  },
  {
    "category": "bottom",
    "title": "Track Pants",
    "price": 181.85
  },
  {
    "category": "bottom",
    "title": "Culottes",
    "price": 129.92
  },
  {
    "category": "shoes",
    "title": "Stilettos",
    "price": 53.43
  },
  {
    "category": "shoes",
    "title": "Sandals",
    "price": 36.55
  },
  {
    "category": "shoes",
    "title": "Running Shoes",
    "price": 25.87
  },
  {
    "category": "shoes",
    "title": "Platform Sneakers",
    "price": 147.59
  },
  {
    "category": "shoes",
    "title": "High Heels",
    "price": 127.84
  },
  {
    "category": "shoes",
    "title": "Derby Shoes",
    "price": 80.5
  },
  {
    "category": "shoes",
    "title": "Platform Sneakers",
    "price": 186.8
  },
  {
    "category": "shoes",
    "title": "Combat Boots",
    "price": 14.77
  },
  {
    "category": "shoes",
    "title": "Chelsea Boots",
    "price": 107.58
  },
  {
    "category": "shoes",
    "title": "Espadrilles",
    "price": 145.46
  },
  {
    "category": "shoes",
    "title": "Platform Sneakers",
    "price": 148.33
  },
  {
    "category": "shoes",
    "title": "Boat Shoes",
    "price": 28.2
  },
  {
    "category": "shoes",
    "title": "Stilettos",
    "price": 139.27
  },
  {
    "category": "shoes",
    "title": "Platform Sneakers",
    "price": 50.2
  },
  {
    "category": "shoes",
    "title": "Wedge Heels",
    "price": 100.67
  },
  {
    "category": "shoes",
    "title": "Hiking Boots",
    "price": 42.18
  },
  {
    "category": "shoes",
    "title": "Derby Shoes",
    "price": 131.47
  },
  {
    "category": "shoes",
    "title": "Boat Shoes",
    "price": 89.72
  },
  {
    "category": "shoes",
    "title": "Flip Flops",
    "price": 118.43
  },
  {
    "category": "shoes",
    "title": "Platform Sneakers",
    "price": 77.03
  },
  {
    "category": "shoes",
    "title": "Espadrilles",
    "price": 54.8
  },
  {
    "category": "shoes",
    "title": "Canvas Slip-Ons",
    "price": 144.86
  },
  {
    "category": "shoes",
    "title": "Hiking Boots",
    "price": 72.3
  },
  {
    "category": "shoes",
    "title": "Chelsea Boots",
    "price": 106.94
  },
  {
    "category": "shoes",
    "title": "Boat Shoes",
    "price": 69.7
  },
  {
    "category": "shoes",
    "title": "Dress Oxfords",
    "price": 72.91
  },
  {
    "category": "shoes",
    "title": "Combat Boots",
    "price": 58.15
  },
  {
    "category": "shoes",
    "title": "Hiking Boots",
    "price": 198.28
  },
  {
    "category": "shoes",
    "title": "Espadrilles",
    "price": 27.36
  },
  {
    "category": "shoes",
    "title": "Leather Loafers",
    "price": 159.97
  },
  {
    "category": "shoes",
    "title": "Ballet Flats",
    "price": 73.69
  },
  {
    "category": "shoes",
    "title": "Classic Sneakers",
    "price": 177.24
  },
  {
    "category": "shoes",
    "title": "Hiking Boots",
    "price": 119.61
  },
  {
    "category": "shoes",
    "title": "Wedge Heels",
    "price": 122.92
  },
  {
    "category": "shoes",
    "title": "Flip Flops",
    "price": 70.72
  },
  {
    "category": "shoes",
    "title": "Wedge Heels",
    "price": 139.4
  },
  {
    "category": "shoes",
    "title": "Canvas Slip-Ons",
    "price": 79.16
  },
  {
    "category": "shoes",
    "title": "Running Shoes",
    "price": 16.53
  },
  {
    "category": "shoes",
    "title": "Flip Flops",
    "price": 187.42
  },
  {
    "category": "shoes",
    "title": "Running Shoes",
    "price": 45.18
  },
  {
    "category": "shoes",
    "title": "Leather Loafers",
    "price": 10.54
  },
  {
    "category": "shoes",
    "title": "Leather Loafers",
    "price": 87.32
  },
  {
    "category": "shoes",
    "title": "Ballet Flats",
    "price": 79.69
  },
  {
    "category": "shoes",
    "title": "Canvas Slip-Ons",
    "price": 190.17
  },
  {
    "category": "shoes",
    "title": "Flip Flops",
    "price": 75.54
  },
  {
    "category": "shoes",
    "title": "Espadrilles",
    "price": 68.55
  },
  {
    "category": "shoes",
    "title": "High Heels",
    "price": 22.29
  },
  {
    "category": "shoes",
    "title": "Platform Sneakers",
    "price": 71.78
  },
  {
    "category": "shoes",
    "title": "Classic Sneakers",
    "price": 189.28
  },
  {
    "category": "shoes",
    "title": "Ballet Flats",
    "price": 143.78
  },
  {
    "category": "shoes",
    "title": "Espadrilles",
    "price": 45.34
  },
  {
    "category": "shoes",
    "title": "High Heels",
    "price": 18.34
  },
  {
    "category": "shoes",
    "title": "Dress Oxfords",
    "price": 89.9
  },
  {
    "category": "shoes",
    "title": "Leather Loafers",
    "price": 184.65
  },
  {
    "category": "shoes",
    "title": "Platform Sneakers",
    "price": 36.38
  },
  {
    "category": "shoes",
    "title": "Classic Sneakers",
    "price": 51.36
  },
  {
    "category": "shoes",
    "title": "High Heels",
    "price": 124.94
  },
  {
    "category": "shoes",
    "title": "Stilettos",
    "price": 96.28
  },
  {
    "category": "shoes",
    "title": "Combat Boots",
    "price": 53.88
  },
  {
    "category": "shoes",
    "title": "Boat Shoes",
    "price": 134.11
  },
  {
    "category": "shoes",
    "title": "Platform Sneakers",
    "price": 190.26
  },
  {
    "category": "shoes",
    "title": "Ankle Boots",
    "price": 54.52
  },
  {
    "category": "shoes",
    "title": "Derby Shoes",
    "price": 187.61
  },
  {
    "category": "shoes",
    "title": "Dress Oxfords",
    "price": 132.28
  },
  {
    "category": "shoes",
    "title": "Canvas Slip-Ons",
    "price": 54.07
  },
  {
    "category": "shoes",
    "title": "Ballet Flats",
    "price": 64.99
  },
  {
    "category": "shoes",
    "title": "Boat Shoes",
    "price": 98.43
  },
  {
    "category": "shoes",
    "title": "Moccasins",
    "price": 105.84
  },
  {
    "category": "shoes",
    "title": "Running Shoes",
    "price": 74.24
  },
  {
    "category": "shoes",
    "title": "Derby Shoes",
    "price": 82.7
  },
  {
    "category": "shoes",
    "title": "Sandals",
    "price": 104.0
  },
  {
    "category": "shoes",
    "title": "High Heels",
    "price": 147.96
  },
  {
    "category": "shoes",
    "title": "Canvas Slip-Ons",
    "price": 150.4
  },
  {
    "category": "shoes",
    "title": "Espadrilles",
    "price": 145.88
  },
  {
    "category": "shoes",
    "title": "High Heels",
    "price": 27.83
  },
  {
    "category": "shoes",
    "title": "Canvas Slip-Ons",
    "price": 86.95
  },
  {
    "category": "shoes",
    "title": "Stilettos",
    "price": 149.19
  },
  {
    "category": "shoes",
    "title": "High Heels",
    "price": 117.24
  },
  {
    "category": "shoes",
    "title": "Espadrilles",
    "price": 163.78
  },
  {
    "category": "shoes",
    "title": "Leather Loafers",
    "price": 102.09
  },
  {
    "category": "shoes",
    "title": "Canvas Slip-Ons",
    "price": 137.41
  },
  {
    "category": "shoes",
    "title": "Hiking Boots",
    "price": 11.03
  },
  {
    "category": "shoes",
    "title": "Boat Shoes",
    "price": 38.67
  },
  {
    "category": "shoes",
    "title": "Hiking Boots",
    "price": 111.63
  },
  {
    "category": "shoes",
    "title": "Running Shoes",
    "price": 39.51
  },
  {
    "category": "shoes",
    "title": "Combat Boots",
    "price": 186.55
  },
  {
    "category": "shoes",
    "title": "Combat Boots",
    "price": 97.9
  },
  {
    "category": "shoes",
    "title": "Combat Boots",
    "price": 177.81
  },
  {
    "category": "shoes",
    "title": "Ankle Boots",
    "price": 13.09
  },
  {
    "category": "shoes",
    "title": "Chelsea Boots",
    "price": 193.73
  },
  {
    "category": "shoes",
    "title": "Hiking Boots",
    "price": 60.02
  },
  {
    "category": "shoes",
    "title": "Moccasins",
    "price": 83.01
  },
  {
    "category": "shoes",
    "title": "Canvas Slip-Ons",
    "price": 129.05
  },
  {
    "category": "shoes",
    "title": "Hiking Boots",
    "price": 40.16
  },
  {
    "category": "shoes",
    "title": "Dress Oxfords",
    "price": 73.89
  },
  {
    "category": "shoes",
    "title": "Chelsea Boots",
    "price": 48.83
  },
  {
    "category": "shoes",
    "title": "Derby Shoes",
    "price": 141.05
  },
  {
    "category": "shoes",
    "title": "Canvas Slip-Ons",
    "price": 70.82
  },
  {
    "category": "shoes",
    "title": "Ankle Boots",
    "price": 167.92
  },
  {
    "category": "shoes",
    "title": "Boat Shoes",
    "price": 53.67
  },
  {
    "category": "accessory",
    "title": "Woven Hat",
    "price": 19.13
  },
  {
    "category": "accessory",
    "title": "Baseball Cap",
    "price": 120.46
  },
  {
    "category": "accessory",
    "title": "Baseball Cap",
    "price": 143.84
  },
  {
    "category": "accessory",
    "title": "Pendant Necklace",
    "price": 198.54
  },
  {
    "category": "accessory",
    "title": "Woven Hat",
    "price": 78.3
  },
  {
    "category": "accessory",
    "title": "Silk Scarf",
    "price": 106.69
  },
  {
    "category": "accessory",
    "title": "Leather Wallet",
    "price": 135.09
  },
  {
    "category": "accessory",
    "title": "Baseball Cap",
    "price": 169.98
  },
  {
    "category": "accessory",
    "title": "Leather Gloves",
    "price": 39.2
  },
  {
    "category": "accessory",
    "title": "Beret",
    "price": 132.11
  },
  {
    "category": "accessory",
    "title": "Leather Gloves",
    "price": 187.38
  },
  {
    "category": "accessory",
    "title": "Patterned Socks",
    "price": 155.51
  },
  {
    "category": "accessory",
    "title": "Leather Belt",
    "price": 29.23
  },
  {
    "category": "accessory",
    "title": "Pendant Necklace",
    "price": 155.85
  },
  {
    "category": "accessory",
    "title": "Leather Belt",
    "price": 168.53
  },
  {
    "category": "accessory",
    "title": "Crossbody Bag",
    "price": 36.58
  },
  {
    "category": "accessory",
    "title": "Pendant Necklace",
    "price": 66.84
  },
  {
    "category": "accessory",
    "title": "Bracelet Set",
    "price": 164.18
  },
  {
    "category": "accessory",
    "title": "Pendant Necklace",
    "price": 18.67
  },
  {
    "category": "accessory",
    "title": "Pendant Necklace",
    "price": 189.55
  },
  {
    "category": "accessory",
    "title": "Wristwatch",
    "price": 72.22
  },
  {
    "category": "accessory",
    "title": "Leather Wallet",
    "price": 154.8
  },
  {
    "category": "accessory",
    "title": "Baseball Cap",
    "price": 196.52
  },
  {
    "category": "accessory",
    "title": "Silk Scarf",
    "price": 58.95
  },
  {
    "category": "accessory",
    "title": "Beret",
    "price": 53.61
  },
  {
    "category": "accessory",
    "title": "Baseball Cap",
    "price": 140.44
  },
  {
    "category": "accessory",
    "title": "Bracelet Set",
    "price": 120.82
  },
  {
    "category": "accessory",
    "title": "Statement Necklace",
    "price": 194.17
  },
  {
    "category": "accessory",
    "title": "Canvas Backpack",
    "price": 72.66
  },
  {
    "category": "accessory",
    "title": "Beret",
    "price": 171.5
  },
  {
    "category": "accessory",
    "title": "Woven Hat",
    "price": 194.48
  },
  {
    "category": "accessory",
    "title": "Silk Scarf",
    "price": 76.57
  },
  {
    "category": "accessory",
    "title": "Canvas Backpack",
    "price": 45.19
  },
  {
    "category": "accessory",
    "title": "Patterned Socks",
    "price": 68.84
  },
  {
    "category": "accessory",
    "title": "Bow Tie",
    "price": 154.26
  },
  {
    "category": "accessory",
    "title": "Aviator Sunglasses",
    "price": 71.65
  },
  {
    "category": "accessory",
    "title": "Stud Earrings",
    "price": 32.35
  },
  {
    "category": "accessory",
    "title": "Canvas Backpack",
    "price": 17.85
  },
  {
    "category": "accessory",
    "title": "Canvas Backpack",
    "price": 135.8
  },
  {
    "category": "accessory",
    "title": "Pendant Necklace",
    "price": 171.01
  },
  {
    "category": "accessory",
    "title": "Aviator Sunglasses",
    "price": 15.44
  },
  {
    "category": "accessory",
    "title": "Leather Gloves",
    "price": 188.48
  },
  {
    "category": "accessory",
    "title": "Patterned Socks",
    "price": 193.17
  },
  {
    "category": "accessory",
    "title": "Beret",
    "price": 59.7
  },
  {
    "category": "accessory",
    "title": "Knit Beanie",
    "price": 139.38
  },
  {
    "category": "accessory",
    "title": "Stud Earrings",
    "price": 25.86
  },
  {
    "category": "accessory",
    "title": "Leather Gloves",
    "price": 181.02
  },
  {
    "category": "accessory",
    "title": "Wristwatch",
    "price": 154.14
  },
  {
    "category": "accessory",
    "title": "Tote Bag",
    "price": 44.42
  },
  {
    "category": "accessory",
    "title": "Silk Scarf",
    "price": 113.75
  },
  {
    "category": "accessory",
    "title": "Canvas Backpack",
    "price": 68.87
  },
  {
    "category": "accessory",
    "title": "Pendant Necklace",
    "price": 165.86
  },
  {
    "category": "accessory",
    "title": "Woven Hat",
    "price": 82.96
  },
  {
    "category": "accessory",
    "title": "Clutch Purse",
    "price": 13.31
  },
  {
    "category": "accessory",
    "title": "Statement Necklace",
    "price": 145.22
  },
  {
    "category": "accessory",
    "title": "Bow Tie",
    "price": 150.0
  },
  {
    "category": "accessory",
    "title": "Bow Tie",
    "price": 83.07
  },
  {
    "category": "accessory",
    "title": "Silk Scarf",
    "price": 55.04
  },
  {
    "category": "accessory",
    "title": "Tote Bag",
    "price": 130.06
  },
  {
    "category": "accessory",
    "title": "Baseball Cap",
    "price": 69.22
  },
  {
    "category": "accessory",
    "title": "Beret",
    "price": 144.98
  },
  {
    "category": "accessory",
    "title": "Aviator Sunglasses",
    "price": 175.87
  },
  {
    "category": "accessory",
    "title": "Bracelet Set",
    "price": 40.35
  },
  {
    "category": "accessory",
    "title": "Aviator Sunglasses",
    "price": 82.94
  },
  {
    "category": "accessory",
    "title": "Crossbody Bag",
    "price": 98.76
  },
  {
    "category": "accessory",
    "title": "Stud Earrings",
    "price": 80.91
  },
  {
    "category": "accessory",
    "title": "Silk Scarf",
    "price": 71.78
  },
  {
    "category": "accessory",
    "title": "Baseball Cap",
    "price": 29.97
  },
  {
    "category": "accessory",
    "title": "Canvas Backpack",
    "price": 24.77
  },
  {
    "category": "accessory",
    "title": "Leather Belt",
    "price": 34.01
  },
  {
    "category": "accessory",
    "title": "Wristwatch",
    "price": 186.52
  },
  {
    "category": "accessory",
    "title": "Patterned Socks",
    "price": 159.44
  },
  {
    "category": "accessory",
    "title": "Knit Beanie",
    "price": 148.7
  },
  {
    "category": "accessory",
    "title": "Clutch Purse",
    "price": 129.27
  },
  {
    "category": "accessory",
    "title": "Pendant Necklace",
    "price": 56.21
  },
  {
    "category": "accessory",
    "title": "Leather Belt",
    "price": 103.79
  },
  {
    "category": "accessory",
    "title": "Leather Belt",
    "price": 193.8
  },
  {
    "category": "accessory",
    "title": "Baseball Cap",
    "price": 36.8
  },
  {
    "category": "accessory",
    "title": "Clutch Purse",
    "price": 45.29
  },
  {
    "category": "accessory",
    "title": "Woven Hat",
    "price": 107.51
  },
  {
    "category": "accessory",
    "title": "Statement Necklace",
    "price": 113.66
  },
  {
    "category": "accessory",
    "title": "Leather Gloves",
    "price": 115.82
  },
  {
    "category": "accessory",
    "title": "Beret",
    "price": 122.39
  },
  {
    "category": "accessory",
    "title": "Baseball Cap",
    "price": 103.38
  },
  {
    "category": "accessory",
    "title": "Leather Wallet",
    "price": 122.16
  },
  {
    "category": "accessory",
    "title": "Crossbody Bag",
    "price": 130.15
  },
  {
    "category": "accessory",
    "title": "Tote Bag",
    "price": 70.21
  },
  {
    "category": "accessory",
    "title": "Baseball Cap",
    "price": 123.67
  },
  {
    "category": "accessory",
    "title": "Statement Necklace",
    "price": 160.64
  },
  {
    "category": "accessory",
    "title": "Knit Beanie",
    "price": 182.65
  },
  {
    "category": "accessory",
    "title": "Baseball Cap",
    "price": 85.66
  },
  {
    "category": "accessory",
    "title": "Silk Scarf",
    "price": 187.39
  },
  {
    "category": "accessory",
    "title": "Clutch Purse",
    "price": 180.3
  },
  {
    "category": "accessory",
    "title": "Stud Earrings",
    "price": 174.47
  },
  {
    "category": "accessory",
    "title": "Tote Bag",
    "price": 183.28
  },
  {
    "category": "accessory",
    "title": "Statement Necklace",
    "price": 137.97
  },
  {
    "category": "accessory",
    "title": "Tote Bag",
    "price": 83.88
  },
  {
    "category": "accessory",
    "title": "Leather Belt",
    "price": 113.05
  },
  {
    "category": "accessory",
    "title": "Aviator Sunglasses",
    "price": 74.51
  },
  {
    "category": "accessory",
    "title": "Aviator Sunglasses",
    "price": 116.92
  }
]